gpg_multiple_signatures/__init__.py
gpg_multiple_signatures/gpg_multiple_signatures.py
gpg_multiple_signatures/gpg_multiple_verifications.py
gpg_multiple_signatures/parser.py
gpg_multiple_signatures/frontend/__init__.py
gpg_multiple_signatures/frontend/columns.py
gpg_multiple_signatures/frontend/common.py
gpg_multiple_signatures/frontend/progress_table.py
gpg_multiple_signatures/frontend/signatures.py
gpg_multiple_signatures/frontend/utils.py
gpg_multiple_signatures/frontend/verifications.py
gpg_multiple_signatures-2.3.1.dist-info/METADATA
gpg_multiple_signatures-2.3.1.dist-info/WHEEL
gpg_multiple_signatures-2.3.1.dist-info/entry_points.txt
gpg_multiple_signatures-2.3.1.dist-info/top_level.txt
gpg_multiple_signatures-2.3.1.dist-info/zip-safe
gpg_multiple_signatures-2.3.1.dist-info/RECORD
